pocoglot/__init__.py
pocoglot/cli.py
pocoglot/languages/__init__.py
pocoglot/languages/csharp.py
pocoglot/languages/golang.py
pocoglot/languages/java.py
pocoglot/languages/php8.py
pocoglot/languages/python3.py
pocoglot/languages/typescript.py
pocoglot/templates/csharp.jinja
pocoglot/templates/golang.jinja
pocoglot/templates/java.jinja
pocoglot/templates/php8.jinja
pocoglot/templates/python3.jinja
pocoglot/templates/typescript.jinja
pocoglot-0.9.1.dist-info/LICENSE.md
pocoglot-0.9.1.dist-info/METADATA
pocoglot-0.9.1.dist-info/WHEEL
pocoglot-0.9.1.dist-info/entry_points.txt
pocoglot-0.9.1.dist-info/top_level.txt
pocoglot-0.9.1.dist-info/RECORD
