Metadata-Version: 2.1
Name: pocoglot
Version: 0.9.1
Summary: Pocoglot generates POCOs in multiple languages from a YAML definition file.
Home-page: https://github.com/reconmap/pocoglot
Author: Santiago Lizardo
Author-email: santiagolizardo@users.noreply.github.com
License: MIT license
Keywords: codegen model entity golang php csharp yaml
Classifier: Development Status :: 5 - Production/Stable
Classifier: Environment :: Console
Classifier: Programming Language :: Python :: 3
Requires-Python: >=3.9
License-File: LICENSE.md
Requires-Dist: coloredlogs
Requires-Dist: Jinja2
Requires-Dist: click
